caselawclient/Client.py
caselawclient/__init__.py
caselawclient/client_helpers/__init__.py
caselawclient/client_helpers/search_helpers.py
caselawclient/content_hash.py
caselawclient/errors.py
caselawclient/factories.py
caselawclient/identifier_resolution.py
caselawclient/managers/__init__.py
caselawclient/managers/merge/__init__.py
caselawclient/managers/merge/checks.py
caselawclient/models/__init__.py
caselawclient/models/documents/__init__.py
caselawclient/models/documents/body.py
caselawclient/models/documents/comparison.py
caselawclient/models/documents/exceptions.py
caselawclient/models/documents/statuses.py
caselawclient/models/documents/stub.py
caselawclient/models/documents/templates/judgment.xml
caselawclient/models/documents/templates/original.xml
caselawclient/models/documents/transforms/html.xsl
caselawclient/models/documents/versions.py
caselawclient/models/documents/xml.py
caselawclient/models/identifiers/__init__.py
caselawclient/models/identifiers/collection.py
caselawclient/models/identifiers/exceptions.py
caselawclient/models/identifiers/fclid.py
caselawclient/models/identifiers/neutral_citation.py
caselawclient/models/identifiers/press_summary_ncn.py
caselawclient/models/identifiers/unpacker.py
caselawclient/models/judgments.py
caselawclient/models/neutral_citation_mixin.py
caselawclient/models/parser_logs.py
caselawclient/models/press_summaries.py
caselawclient/models/utilities/__init__.py
caselawclient/models/utilities/aws.py
caselawclient/models/utilities/dates.py
caselawclient/models/utilities/move.py
caselawclient/py.typed
caselawclient/responses/__init__.py
caselawclient/responses/search_response.py
caselawclient/responses/search_result.py
caselawclient/responses/xsl/search_match.xsl
caselawclient/search_parameters.py
caselawclient/types.py
caselawclient/xml_helpers.py
caselawclient/xquery/break_judgment_checkout.xqy
caselawclient/xquery/check_content_hash_unique_by_uri.xqy
caselawclient/xquery/checkin_judgment.xqy
ds_caselaw_marklogic_api_client-44.4.1.dist-info/LICENSE.md
ds_caselaw_marklogic_api_client-44.4.1.dist-info/METADATA
ds_caselaw_marklogic_api_client-44.4.1.dist-info/WHEEL
ds_caselaw_marklogic_api_client-44.4.1.dist-info/RECORD
