Metadata-Version: 2.3
Name: ds-caselaw-marklogic-api-client
Version: 44.4.1
Summary: An API client for interacting with the underlying data in Find Caselaw.
Keywords: national archives,caselaw
Author: The National Archives
Requires-Python: >=3.12.0,<4.0.0
Classifier: Programming Language :: Python :: 3
Classifier: Programming Language :: Python :: 3.12
Classifier: Programming Language :: Python :: 3.13
Requires-Dist: boto3 (>=1.26.112,<2.0.0)
Requires-Dist: certifi (>=2025.11.12,<2025.12.0)
Requires-Dist: charset-normalizer (>=3.0.0,<4.0.0)
Requires-Dist: defusedxml (>=0.7.1,<0.8.0)
Requires-Dist: django-environ (>=0.12.0)
Requires-Dist: ds-caselaw-utils (>=2.10.0,<3.0.0)
Requires-Dist: idna (>=3.4,<4.0)
Requires-Dist: lxml (>=6.0.0,<7.0.0)
Requires-Dist: memoization (>=0.4.0,<0.5.0)
Requires-Dist: mypy-boto3-s3 (>=1.26.104,<2.0.0)
Requires-Dist: mypy-boto3-sns (>=1.26.69,<2.0.0)
Requires-Dist: pydantic (>=2.12.3,<3.0.0)
Requires-Dist: python-dateutil (>=2.9.0-post.0,<3.0.0)
Requires-Dist: pytz (>2024)
Requires-Dist: requests (>=2.28.2,<3.0.0)
Requires-Dist: requests-toolbelt (>=0.10.1,<1.1.0)
Requires-Dist: saxonche (>=12.5.0,<13.0.0)
Requires-Dist: sqids (>=0.5.0,<0.6.0)
Requires-Dist: typing-extensions (>=4.7.1,<5.0.0)
Project-URL: Homepage, https://github.com/nationalarchives/ds-caselaw-custom-api-client
